[
    {
        "id": 1,
        "title": "Reusable Water Bottle",
        "image": "https://i.ibb.co.com/yQjnF43/c5bf91625e4da18b73951944788bb3d6-jpg-960x960q80-jpg.webp",
        "description": "A durable, BPA-free bottle for reducing plastic waste."
    },
    {
        "id": 2,
        "title": "Biodegradable Bag",
        "image": "https://i.ibb.co.com/sjNSV2H/61-Y47j-WA1b-L-AC-SX679.jpg",
        "description": "A compostable bag for all your shopping needs."
    },
    {
        "id": 3,
        "title": "Solar-Powered Charger",
        "image": "https://i.ibb.co.com/vjTVRDC/71q-UURVf0w-L-AC-SX679.jpg",
        "description": "Charge your devices sustainably with solar energy."
    }
]